[
    {
        "id": "inspiro-lite-why-us",
        "name": "Why Us?",
        "theme": "Inspiro Lite",
        "category": "features",
        "thumbnail": "inspiro-lite/why-us",
        "filename": "inspiro-lite-why-us.json"
    },
    {
        "id": "inspiro-lite-hero",
        "name": "Hero Minimal",
        "theme": "Inspiro Lite",
        "category": "hero",
        "thumbnail": "inspiro-lite/hero-minimal",
        "filename": "inspiro-lite-hero.json"
    },
    {
        "id": "inspiro-lite-about-agency",
        "name": "About Agency",
        "theme": "Inspiro Lite",
        "category": "general",
        "thumbnail": "inspiro-lite/about-agency",
        "filename": "inspiro-lite-about-agency.json"
    },
    {
        "id": "inspiro-lite-services",
        "name": "Our Services",
        "theme": "Inspiro Lite",
        "category": "features",
        "thumbnail": "inspiro-lite/services",
        "filename": "inspiro-lite-services.json"
    },
    {
        "id": "inspiro-lite-team",
        "name": "Our Team",
        "theme": "Inspiro Lite",
        "category": "general",
        "thumbnail": "inspiro-lite/team",
        "filename": "inspiro-lite-team.json"
    },
    {
        "id": "inspiro-lite-blog",
        "name": "Blog",
        "theme": "Inspiro Lite",
        "category": "general",
        "thumbnail": "inspiro-lite/blog",
        "filename": "inspiro-lite-blog.json"
    },
    {
        "id": "inspiro-lite-contact",
        "name": "Contact with Map",
        "theme": "Inspiro Lite",
        "category": "contact",
        "thumbnail": "inspiro-lite/contact",
        "filename": "inspiro-lite-contact.json"
    },
    {
        "id": "inspiro-lite-about",
        "name": "About",
        "theme": "Inspiro Lite",
        "category": "general",
        "thumbnail": "inspiro-lite/about",
        "filename": "inspiro-lite-about.json"
    },
    {
        "id": "inspiro-lite-expertise",
        "name": "Expertise",
        "theme": "Inspiro Lite",
        "category": "features",
        "thumbnail": "inspiro-lite/expertise",
        "filename": "inspiro-lite-expertise.json"
    },
    {
        "id": "charity-counter",
        "name": "Counter Statistics",
        "theme": "Inspiro PRO - Charity",
        "category": "features",
        "thumbnail": "charity/counter",
        "filename": "charity-counter.json"
    },
    {
        "id": "events-pricing-tickets",
        "name": "Pricing / Tickets",
        "theme": "Inspiro Premium - Events",
        "category": "pricing",
        "thumbnail": "events/pricing",
        "filename": "events-pricing-tickets.json"
    },
    {
        "id": "fitness-testimonials",
        "name": "Testimonials",
        "theme": "Inspiro PRO - Fitness",
        "category": "testimonials",
        "thumbnail": "fitness/testimonials",
        "filename": "fitness-testimonials.json"
    },
    {
        "id": "cookbook-newsletter",
        "name": "Newsletter Signup",
        "theme": "CookBook",
        "category": "forms",
        "thumbnail": "cookbook/newsletter",
        "filename": "cookbook-newsletter.json"
    },
    {
        "id": "cookbook-video",
        "name": "Featured Video",
        "theme": "CookBook",
        "category": "media",
        "thumbnail": "cookbook/video",
        "filename": "cookbook-video.json"
    },
    {
        "id": "cookbook-categories",
        "name": "Featured Categories",
        "theme": "CookBook",
        "category": "general",
        "thumbnail": "cookbook/categories",
        "filename": "cookbook-categories.json"
    },
    {
        "id": "business-pricing",
        "name": "Pricing Table",
        "theme": "Inspiro PRO - Business",
        "category": "pricing",
        "thumbnail": "business/pricing",
        "filename": "business-pricing.json"
    },
    {
        "id": "cookbook-shop-products",
        "name": "Shop Products",
        "theme": "CookBook",
        "category": "ecommerce",
        "thumbnail": "cookbook/shop",
        "filename": "cookbook-shop-products.json"
    },
    {
        "id": "winery-booking-cta",
        "name": "Booking CTA",
        "theme": "Inspiro PRO - Winery",
        "category": "cta",
        "thumbnail": "winery/booking",
        "filename": "winery-booking-cta.json"
    },
    {
        "id": "winery-awards",
        "name": "Awards & Recognition",
        "theme": "Inspiro PRO - Winery",
        "category": "general",
        "thumbnail": "winery/awards",
        "filename": "winery-awards.json"
    },
    {
        "id": "events-sponsors",
        "name": "Sponsors",
        "theme": "Inspiro Premium - Events",
        "category": "general",
        "thumbnail": "events/sponsors",
        "filename": "events-sponsors.json"
    },
    {
        "id": "events-schedule",
        "name": "Event Schedule",
        "theme": "Inspiro Premium - Events",
        "category": "general",
        "thumbnail": "events/schedule",
        "filename": "events-schedule.json"
    }
]