{"version":"0.4","title":"About &#8211; Flow 2","type":"page","content":[{"id":"50773f41","settings":{"content_width":{"unit":"px","size":1600,"sizes":[]},"gap":"no","margin":{"unit":"px","top":"100","right":0,"bottom":"40","left":0,"isLinked":false},"padding":{"unit":"px","top":"0","right":"0","bottom":"0","left":"0","isLinked":true}},"elements":[{"id":"45e614e1","settings":{"_column_size":100,"_inline_size":null,"space_between_widgets":0,"margin":{"unit":"px","top":"0","right":"0","bottom":"0","left":"0","isLinked":true},"padding":{"unit":"px","top":"0","right":"0","bottom":"0","left":"0","isLinked":true}},"elements":[{"id":"4f9798cd","settings":{"image_size":"custom","image_custom_dimension":{"width":"1600","height":"980"},"_margin":{"unit":"px","top":"0","right":"0","bottom":"0","left":"0","isLinked":true},"_padding":{"unit":"px","top":"0","right":"0","bottom":"0","left":"0","isLinked":true}},"elements":[],"isInner":false,"widgetType":"image","elType":"widget"}],"isInner":false,"elType":"column"}],"isInner":false,"elType":"section"},{"id":"7ebd94b5","settings":{"content_width":{"unit":"px","size":670,"sizes":[]},"gap":"no","margin":{"unit":"px","top":"0","right":0,"bottom":"86","left":0,"isLinked":false},"padding":{"unit":"px","top":"0","right":"0","bottom":"0","left":"0","isLinked":true}},"elements":[{"id":"63c6e678","settings":{"_column_size":100,"_inline_size":null,"space_between_widgets":0,"margin":{"unit":"px","top":"0","right":"0","bottom":"0","left":"0","isLinked":true},"padding":{"unit":"px","top":"0","right":"0","bottom":"0","left":"0","isLinked":true}},"elements":[{"id":"758fa6d2","settings":{"title":"Our story","title_color":"#888888","typography_typography":"custom","typography_font_size":{"unit":"px","size":24,"sizes":[]},"typography_font_weight":"normal","_margin":{"unit":"px","top":"0","right":"0","bottom":"37","left":"0","isLinked":false},"_padding":{"unit":"px","top":"0","right":"0","bottom":"0","left":"0","isLinked":true}},"elements":[],"isInner":false,"widgetType":"heading","elType":"widget"},{"id":"34360ad3","settings":{"editor":"<p>This is some dummy copy. You\u2019re not really supposed to read this dummy copy, it is just a place holder for people who need some type to visualize what the actual copy might look like if it were real content.<\/p><p>If you want to read, I might suggest a good book, perhaps Melville. That\u2019s why they call it, the dummy copy. This, of course, is not the real copy for this entry. Rest assured, the words will expand the concept. With clarity. Conviction. And a little wit.<\/p><p>In today\u2019s competitive market environment, the body copy of your entry must lead the reader through a series of disarmingly simple thoughts.<\/p>","text_color":"#FFFFFF","typography_typography":"custom","typography_font_size":{"unit":"px","size":20,"sizes":[]},"typography_font_weight":"normal","_margin":{"unit":"px","top":"0","right":"0","bottom":"0","left":"0","isLinked":true},"_padding":{"unit":"px","top":"0","right":"0","bottom":"0","left":"0","isLinked":true}},"elements":[],"isInner":false,"widgetType":"text-editor","elType":"widget"}],"isInner":false,"elType":"column"}],"isInner":false,"elType":"section"},{"id":"719f858a","settings":{"content_width":{"unit":"px","size":670,"sizes":[]},"gap":"no","margin":{"unit":"px","top":"0","right":0,"bottom":"86","left":0,"isLinked":false},"padding":{"unit":"px","top":"0","right":"0","bottom":"0","left":"0","isLinked":true}},"elements":[{"id":"1664e0de","settings":{"_column_size":100,"_inline_size":null,"space_between_widgets":0,"margin":{"unit":"px","top":"0","right":"0","bottom":"0","left":"0","isLinked":true},"padding":{"unit":"px","top":"0","right":"0","bottom":"0","left":"0","isLinked":true}},"elements":[{"id":"6c0db382","settings":{"title":"Awards","title_color":"#888888","typography_typography":"custom","typography_font_size":{"unit":"px","size":24,"sizes":[]},"typography_font_weight":"normal","_margin":{"unit":"px","top":"0","right":"0","bottom":"37","left":"0","isLinked":false},"_padding":{"unit":"px","top":"0","right":"0","bottom":"0","left":"0","isLinked":true}},"elements":[],"isInner":false,"widgetType":"heading","elType":"widget"},{"id":"24939f7d","settings":{"editor":"<p>This is some dummy copy. You\u2019re not really supposed to read this dummy copy, it is just a place holder for people who need some type to visualize what the actual copy might look like if it were real content.<\/p><p>If you want to read, I might suggest a good book, perhaps Melville. That\u2019s why they call it, the dummy copy. This, of course, is not the real copy for this entry. Rest assured, the words will expand the concept. With clarity. Conviction. And a little wit.<\/p><p>In today\u2019s competitive market environment, the body copy of your entry must lead the reader through a series of disarmingly simple thoughts.<\/p>","text_color":"#FFFFFF","typography_typography":"custom","typography_font_size":{"unit":"px","size":20,"sizes":[]},"typography_font_weight":"normal","_margin":{"unit":"px","top":"0","right":"0","bottom":"0","left":"0","isLinked":true},"_padding":{"unit":"px","top":"0","right":"0","bottom":"0","left":"0","isLinked":true}},"elements":[],"isInner":false,"widgetType":"text-editor","elType":"widget"}],"isInner":false,"elType":"column"}],"isInner":false,"elType":"section"},{"id":"62ba9d7d","settings":{"content_width":{"unit":"px","size":670,"sizes":[]},"gap":"no","margin":{"unit":"px","top":"0","right":0,"bottom":"100","left":0,"isLinked":false},"padding":{"unit":"px","top":"0","right":"0","bottom":"0","left":"0","isLinked":true}},"elements":[{"id":"e0f5d19","settings":{"_column_size":100,"_inline_size":null,"space_between_widgets":0,"margin":{"unit":"px","top":"0","right":"0","bottom":"0","left":"0","isLinked":true},"padding":{"unit":"px","top":"0","right":"0","bottom":"0","left":"0","isLinked":true}},"elements":[{"id":"292032a0","settings":{"title":"Brands","title_color":"#888888","typography_typography":"custom","typography_font_size":{"unit":"px","size":24,"sizes":[]},"typography_font_weight":"normal","_margin":{"unit":"px","top":"0","right":"0","bottom":"37","left":"0","isLinked":false},"_padding":{"unit":"px","top":"0","right":"0","bottom":"0","left":"0","isLinked":true}},"elements":[],"isInner":false,"widgetType":"heading","elType":"widget"},{"id":"76af7ce7","settings":{"editor":"<p>This is some dummy copy. You\u2019re not really supposed to read this dummy copy, it is just a place holder for people who need some type to visualize what the actual copy might look like if it were real content.<\/p><p>If you want to read, I might suggest a good book, perhaps Melville. That\u2019s why they call it, the dummy copy. This, of course, is not the real copy for this entry. Rest assured, the words will expand the concept. With clarity. Conviction. And a little wit.<\/p><p>In today\u2019s competitive market environment, the body copy of your entry must lead the reader through a series of disarmingly simple thoughts.<\/p>","text_color":"#FFFFFF","typography_typography":"custom","typography_font_size":{"unit":"px","size":20,"sizes":[]},"typography_font_weight":"normal","_margin":{"unit":"px","top":"0","right":"0","bottom":"0","left":"0","isLinked":true},"_padding":{"unit":"px","top":"0","right":"0","bottom":"0","left":"0","isLinked":true}},"elements":[],"isInner":false,"widgetType":"text-editor","elType":"widget"}],"isInner":false,"elType":"column"}],"isInner":false,"elType":"section"}]}