{"version":"0.4","title":"Homepage &#8211; Flow 1","type":"page","content":[{"id":"4d0d2b74","settings":{"layout":"full_width","gap":"no"},"elements":[{"id":"175e9817","settings":{"_column_size":100,"_inline_size":100,"align":"center","space_between_widgets":0,"margin":{"unit":"px","top":"0","right":"0","bottom":"0","left":"0","isLinked":true},"padding":{"unit":"px","top":"0","right":"0","bottom":"0","left":"0","isLinked":true}},"elements":[{"id":"762f70da","settings":{"slides":[{"image":{"url":"https:\/\/wordpress.local\/wp-content\/plugins\/elementor\/assets\/images\/placeholder.png"},"_id":"60d4868","youtube_url":"https:\/\/www.youtube.com\/watch?v=XHOmBV4js_E","vimeo_url":"https:\/\/vimeo.com\/235215203","dailymotion_url":"https:\/\/www.dailymotion.com\/video\/x6tqhqb","video":"yes","title":"Video Background & Video Lightbox","subtitle":"In Inspiro you can display a self-hosted (MP4), YouTube or Vimeo video in the slideshow background. Videos are also supported in the video lightbox feature and it can be a different video than the one from background."},{"image":{"url":"https:\/\/wordpress.local\/wp-content\/plugins\/elementor\/assets\/images\/placeholder.png"},"_id":"1e3b341","youtube_url":"https:\/\/www.youtube.com\/watch?v=XHOmBV4js_E","vimeo_url":"https:\/\/vimeo.com\/235215203","dailymotion_url":"https:\/\/www.dailymotion.com\/video\/x6tqhqb"},{"image":{"url":"https:\/\/wordpress.local\/wp-content\/plugins\/elementor\/assets\/images\/placeholder.png"},"_id":"778b10c","youtube_url":"https:\/\/www.youtube.com\/watch?v=XHOmBV4js_E","vimeo_url":"https:\/\/vimeo.com\/235215203","dailymotion_url":"https:\/\/www.dailymotion.com\/video\/x6tqhqb"},{"image":{"url":"https:\/\/wordpress.local\/wp-content\/plugins\/elementor\/assets\/images\/placeholder.png"},"_id":"60035f8","youtube_url":"https:\/\/www.youtube.com\/watch?v=XHOmBV4js_E","vimeo_url":"https:\/\/vimeo.com\/235215203","dailymotion_url":"https:\/\/www.dailymotion.com\/video\/x6tqhqb"},{"image":{"url":"https:\/\/wordpress.local\/wp-content\/plugins\/elementor\/assets\/images\/placeholder.png"},"_id":"c4637a1","youtube_url":"https:\/\/www.youtube.com\/watch?v=XHOmBV4js_E","vimeo_url":"https:\/\/vimeo.com\/235215203","dailymotion_url":"https:\/\/www.dailymotion.com\/video\/x6tqhqb"},{"image":{"url":"https:\/\/wordpress.local\/wp-content\/plugins\/elementor\/assets\/images\/placeholder.png"},"_id":"1868196","youtube_url":"https:\/\/www.youtube.com\/watch?v=XHOmBV4js_E","vimeo_url":"https:\/\/vimeo.com\/235215203","dailymotion_url":"https:\/\/www.dailymotion.com\/video\/x6tqhqb"},{"image":{"url":"https:\/\/wordpress.local\/wp-content\/plugins\/elementor\/assets\/images\/placeholder.png"},"_id":"042d83c","youtube_url":"https:\/\/www.youtube.com\/watch?v=XHOmBV4js_E","vimeo_url":"https:\/\/vimeo.com\/235215203","dailymotion_url":"https:\/\/www.dailymotion.com\/video\/x6tqhqb"}],"_margin":{"unit":"px","top":"0","right":"0","bottom":"0","left":"0","isLinked":true},"_padding":{"unit":"px","top":"0","right":"0","bottom":"0","left":"0","isLinked":true},"_element_width":"inherit","autoplay":"","auto_height_max":{"unit":"px","size":1000,"sizes":[]},"arrow_color":"#FFFFFF","_css_classes":"homepage-slider"},"elements":[],"isInner":false,"widgetType":"wpzoom-elementor-addons-slider","elType":"widget"}],"isInner":false,"elType":"column"}],"isInner":false,"elType":"section"},{"id":"395003d0","settings":{"gap":"no","margin":{"unit":"px","top":"0","right":0,"bottom":"0","left":0,"isLinked":true},"padding":{"unit":"px","top":"100","right":"0","bottom":"100","left":"0","isLinked":false}},"elements":[{"id":"6dae7bb8","settings":{"_column_size":100,"_inline_size":null,"space_between_widgets":0},"elements":[{"id":"6edb94e0","settings":{"title":"About us","title_color":"#0BB4AA","typography_typography":"custom","typography_font_size":{"unit":"px","size":36,"sizes":[]},"typography_font_weight":"500","_margin":{"unit":"px","top":"0","right":"0","bottom":"50","left":"0","isLinked":false}},"elements":[],"isInner":false,"widgetType":"heading","elType":"widget"},{"id":"7b83adb1","settings":{"layout":"full_width","content_width":{"unit":"px","size":500,"sizes":[]},"gap":"no","gap_columns_custom":{"unit":"px","size":100,"sizes":[]},"structure":"20"},"elements":[{"id":"2922d759","settings":{"_column_size":50,"_inline_size":58.036,"margin":{"unit":"px","top":"0","right":"0","bottom":"0","left":"0","isLinked":false},"padding":{"unit":"px","top":"0","right":"200","bottom":"0","left":"0","isLinked":false}},"elements":[{"id":"8569c20","settings":{"editor":"<p>This is some dummy copy. You\u2019re not really supposed to read this dummy copy, it is just a place holder for people who need some type to visualize what the actual copy might look like if it were real content.<\/p><p>If you want to read, I might suggest a good book, perhaps Melville. That\u2019s why they call it, the dummy copy. This, of course, is not the real copy for this entry. Rest assured, the words will expand the concept. With clarity. Conviction. And a little wit.<\/p><p>In today\u2019s competitive market environment, the body copy of your entry must lead the reader through a series of disarmingly simple thoughts.<\/p>","text_color":"#FFFFFF","typography_typography":"custom","typography_font_size":{"unit":"px","size":16,"sizes":[]},"typography_font_weight":"normal","typography_line_height":{"unit":"em","size":1.75,"sizes":[]},"typography_letter_spacing":{"unit":"px","size":0,"sizes":[]},"_margin":{"unit":"px","top":"0","right":"0","bottom":"0","left":"0","isLinked":false},"__globals__":{"text_color":""}},"elements":[],"isInner":false,"widgetType":"text-editor","elType":"widget"},{"id":"1a04a5ee","settings":{"text":"Learn more","size":"lg","typography_typography":"custom","typography_font_size":{"unit":"px","size":16,"sizes":[]},"typography_font_weight":"500","button_text_color":"#0BB4AA","background_color":"#00000000","border_border":"solid","border_width":{"unit":"px","top":"1","right":"1","bottom":"1","left":"1","isLinked":true},"border_color":"#0BB4AA","border_radius":{"unit":"px","top":"100","right":"100","bottom":"100","left":"100","isLinked":true},"_margin":{"unit":"px","top":"20","right":"0","bottom":"0","left":"0","isLinked":false}},"elements":[],"isInner":false,"widgetType":"button","elType":"widget"}],"isInner":true,"elType":"column"},{"id":"2617336e","settings":{"_column_size":50,"_inline_size":41.964,"space_between_widgets":0},"elements":[{"id":"7a9ed9e9","settings":{"image_size":"custom","image_custom_dimension":{"width":"470","height":"550"}},"elements":[],"isInner":false,"widgetType":"image","elType":"widget"}],"isInner":true,"elType":"column"}],"isInner":true,"elType":"section"}],"isInner":false,"elType":"column"}],"isInner":false,"elType":"section"},{"id":"7e144171","settings":{"padding":{"unit":"px","top":"100","right":"0","bottom":"100","left":"0","isLinked":false}},"elements":[{"id":"6f07dc4b","settings":{"_column_size":100,"_inline_size":null,"space_between_widgets":0,"margin":{"unit":"px","top":"0","right":"0","bottom":"0","left":"0","isLinked":true},"padding":{"unit":"px","top":"0","right":"0","bottom":"0","left":"0","isLinked":true}},"elements":[{"id":"54f45c5a","settings":{"title":"Selected work","title_color":"#0BB4AA","typography_typography":"custom","typography_font_size":{"unit":"px","size":36,"sizes":[]},"typography_font_weight":"500","_margin":{"unit":"px","top":"0","right":"0","bottom":"40","left":"0","isLinked":false}},"elements":[],"isInner":false,"widgetType":"heading","elType":"widget"},{"id":"46a4393f","settings":{"columns":"2","posts_per_page":4,"meta_data":[],"meta_separator":"\/","show_read_more":"","read_more_text":"Read More \u00c2\u00bb","grid_style_columns_margin":{"unit":"px","size":30,"sizes":[]},"grid_title_style_typography_typography":"custom","grid_title_style_typography_font_size":{"unit":"px","size":24,"sizes":[]},"grid_title_style_typography_font_weight":"500","grid_title_style_color":"#FFFFFF","grid_content_style_typography_typography":"custom","grid_content_style_typography_font_size":{"unit":"px","size":16,"sizes":[]},"grid_content_style_typography_font_weight":"normal","grid_content_style_color":"#888888"},"elements":[],"isInner":false,"widgetType":"wpzoom-elementor-addons-posts-grid","elType":"widget"},{"id":"20d08bb6","settings":{"text":"View all","align":"center","size":"lg","typography_typography":"custom","typography_font_size":{"unit":"px","size":16,"sizes":[]},"typography_font_weight":"500","button_text_color":"#0BB4AA","background_color":"#00000000","border_border":"solid","border_width":{"unit":"px","top":"1","right":"1","bottom":"1","left":"1","isLinked":true},"border_color":"#0BB4AA","border_radius":{"unit":"px","top":"100","right":"100","bottom":"100","left":"100","isLinked":true},"_margin":{"unit":"px","top":"60","right":"0","bottom":"0","left":"0","isLinked":false}},"elements":[],"isInner":false,"widgetType":"button","elType":"widget"}],"isInner":false,"elType":"column"}],"isInner":false,"elType":"section"},{"id":"2b36082c","settings":{"margin":{"unit":"px","top":"0","right":0,"bottom":"0","left":0,"isLinked":true},"padding":{"unit":"px","top":"100","right":"0","bottom":"100","left":"0","isLinked":false}},"elements":[{"id":"5fde397e","settings":{"_column_size":100,"_inline_size":null,"space_between_widgets":0,"margin":{"unit":"px","top":"0","right":"0","bottom":"0","left":"0","isLinked":true},"padding":{"unit":"px","top":"0","right":"0","bottom":"0","left":"0","isLinked":true}},"elements":[{"id":"42a7fa37","settings":{"title":"Buy prints","title_color":"#0BB4AA","typography_typography":"custom","typography_font_size":{"unit":"px","size":36,"sizes":[]},"typography_font_weight":"500","_margin":{"unit":"px","top":"0","right":"0","bottom":"40","left":"0","isLinked":false},"_padding":{"unit":"px","top":"0","right":"0","bottom":"0","left":"0","isLinked":true}},"elements":[],"isInner":false,"widgetType":"heading","elType":"widget"},{"id":"3c7b2b82","settings":{"_margin":{"unit":"px","top":"0","right":"0","bottom":"0","left":"0","isLinked":true},"_padding":{"unit":"px","top":"0","right":"0","bottom":"0","left":"0","isLinked":true},"item_padding":{"unit":"px","top":"0","right":"0","bottom":"0","left":"0","isLinked":true},"item_margin":{"unit":"%","top":"0","right":"3.9","bottom":"0","left":"0","isLinked":false},"image_margin":{"unit":"px","top":"0","right":"0","bottom":"0","left":"0","isLinked":true},"category_typography_typography":"custom","category_typography_font_size":{"unit":"px","size":16,"sizes":[]},"category_typography_font_weight":"500","title_typography_typography":"custom","title_typography_font_size":{"unit":"px","size":24,"sizes":[]},"title_typography_font_weight":"500","title_color":"#FFFFFF","title_hover_color":"#0BB4AA","title_margin":{"unit":"px","top":"0","right":"0","bottom":"0","left":"0","isLinked":true},"price_color":"#FFFFFF","price_typography_typography":"custom","price_typography_font_size":{"unit":"px","size":16,"sizes":[]},"price_typography_font_weight":"600","del_price_color":"#FFFFFF","del_price_typography_typography":"custom","del_price_typography_font_size":{"unit":"px","size":16,"sizes":[]},"del_price_typography_font_weight":"600","button_typography_typography":"custom","button_typography_font_size":{"unit":"px","size":16,"sizes":[]},"button_typography_font_weight":"600","button_typography_text_transform":"none","button_background_color":"#00000000","button_text_color":"#FFFFFF","button_border_border":"solid","button_border_width":{"unit":"px","top":"0","right":"0","bottom":"0","left":"0","isLinked":true},"button_border_radius":{"unit":"px","top":"0","right":"0","bottom":"0","left":"0","isLinked":true},"button_padding":{"unit":"px","top":"0","right":"0","bottom":"0","left":"0","isLinked":true},"button_margin":{"unit":"px","top":"15","right":"0","bottom":"0","left":"0","isLinked":false},"badge_typography_typography":"custom","badge_typography_font_size":{"unit":"px","size":16,"sizes":[]},"badge_typography_font_weight":"600","price_border_border":"solid","price_border_width":{"unit":"px","top":"1","right":"0","bottom":"0","left":"0","isLinked":false},"price_border_color":"#FFFFFF40","price_padding":{"unit":"px","top":"8","right":"20","bottom":"0","left":"0","isLinked":false},"price_margin":{"unit":"px","top":"0","right":"0","bottom":"0","left":"0","isLinked":false},"posts_per_page":4},"elements":[],"isInner":false,"widgetType":"wpzoom-elementor-addons-woo-products","elType":"widget"}],"isInner":false,"elType":"column"}],"isInner":false,"elType":"section"},{"id":"7210ffcb","settings":{"gap":"no","background_overlay_background":"classic","background_overlay_image":{"url":"https:\/\/wordpress.local\/wp-content\/uploads\/2016\/01\/eiliv-sonas-aceron-1465222-unsplash-1-scaled.jpg","id":6073},"background_overlay_position":"center center","background_overlay_repeat":"no-repeat","background_overlay_size":"cover","css_filters_brightness":{"unit":"px","size":80,"sizes":[]},"css_filters_contrast":{"unit":"px","size":0,"sizes":[]},"margin":{"unit":"px","top":"0","right":0,"bottom":"0","left":0,"isLinked":true},"padding":{"unit":"px","top":"100","right":"0","bottom":"100","left":"0","isLinked":false}},"elements":[{"id":"5f5462c6","settings":{"_column_size":100,"_inline_size":null,"space_between_widgets":0,"margin":{"unit":"px","top":"0","right":"0","bottom":"0","left":"0","isLinked":true},"padding":{"unit":"px","top":"0","right":"0","bottom":"0","left":"0","isLinked":true}},"elements":[{"id":"32e1a23c","settings":{"gap":"no","structure":"20","margin":{"unit":"px","top":"0","right":0,"bottom":"0","left":0,"isLinked":true},"padding":{"unit":"px","top":"0","right":"0","bottom":"0","left":"0","isLinked":true}},"elements":[{"id":"10d9eda1","settings":{"_column_size":50,"_inline_size":45,"space_between_widgets":0,"margin":{"unit":"px","top":"0","right":"0","bottom":"0","left":"0","isLinked":true},"padding":{"unit":"px","top":"0","right":"0","bottom":"0","left":"0","isLinked":true}},"elements":[{"id":"4c955778","settings":{"title":"Example <br\/>\nof hero banner","title_color":"#0BB4AA","typography_typography":"custom","typography_font_size":{"unit":"px","size":60,"sizes":[]},"typography_font_weight":"500","typography_line_height":{"unit":"em","size":1.2,"sizes":[]},"_margin":{"unit":"px","top":"0","right":"0","bottom":"25","left":"0","isLinked":false},"_padding":{"unit":"px","top":"0","right":"0","bottom":"0","left":"0","isLinked":true},"_background_background":"classic"},"elements":[],"isInner":false,"widgetType":"heading","elType":"widget"},{"id":"5ffa14a0","settings":{"editor":"<p>This is some dummy copy. You\u2019re not really supposed to read this dummy copy, it is just a place holder for people who need some type to visualize what the actual copy might look like if it were real content.<\/p>","text_color":"#FFFFFF","typography_typography":"custom","typography_font_size":{"unit":"px","size":16,"sizes":[]},"typography_font_weight":"normal","typography_line_height":{"unit":"em","size":1.75,"sizes":[]},"_margin":{"unit":"px","top":"0","right":"0","bottom":"0","left":"0","isLinked":true},"_padding":{"unit":"px","top":"0","right":"0","bottom":"0","left":"0","isLinked":true}},"elements":[],"isInner":false,"widgetType":"text-editor","elType":"widget"}],"isInner":true,"elType":"column"},{"id":"2ce31423","settings":{"_column_size":50,"_inline_size":54.956,"space_between_widgets":0,"margin":{"unit":"px","top":"0","right":"0","bottom":"0","left":"0","isLinked":true},"padding":{"unit":"px","top":"0","right":"0","bottom":"0","left":"0","isLinked":true}},"elements":[],"isInner":true,"elType":"column"}],"isInner":true,"elType":"section"}],"isInner":false,"elType":"column"}],"isInner":false,"elType":"section"},{"id":"7714cdf5","settings":{"gap":"no","margin":{"unit":"px","top":"0","right":0,"bottom":"0","left":0,"isLinked":true},"padding":{"unit":"px","top":"100","right":"0","bottom":"0","left":"0","isLinked":false}},"elements":[{"id":"1a87cfe3","settings":{"_column_size":100,"_inline_size":null,"space_between_widgets":0,"margin":{"unit":"px","top":"0","right":"0","bottom":"0","left":"0","isLinked":true},"padding":{"unit":"px","top":"0","right":"0","bottom":"0","left":"0","isLinked":true}},"elements":[{"id":"4f7bd058","settings":{"title":"Our team","title_color":"#0BB4AA","typography_typography":"custom","typography_font_size":{"unit":"px","size":36,"sizes":[]},"typography_font_weight":"500","_margin":{"unit":"px","top":"0","right":"0","bottom":"50","left":"0","isLinked":false},"_padding":{"unit":"px","top":"0","right":"0","bottom":"0","left":"0","isLinked":true}},"elements":[],"isInner":false,"widgetType":"heading","elType":"widget"}],"isInner":false,"elType":"column"}],"isInner":false,"elType":"section"},{"id":"36517c61","settings":{"content_width":{"unit":"px","size":1170,"sizes":[]},"gap":"custom","gap_columns_custom":{"unit":"px","size":15,"sizes":[]},"structure":"30","margin":{"unit":"px","top":"0","right":0,"bottom":"0","left":0,"isLinked":true},"padding":{"unit":"px","top":"0","right":"0","bottom":"100","left":"0","isLinked":false}},"elements":[{"id":"15b5acc6","settings":{"_column_size":33,"_inline_size":null,"space_between_widgets":0,"margin":{"unit":"px","top":"0","right":"0","bottom":"0","left":"0","isLinked":true},"padding":{"unit":"px","top":"0","right":"0","bottom":"0","left":"0","isLinked":true}},"elements":[{"id":"63ff1eff","settings":{"title":"Bill Bolduc","job_title":"CEO","bio":"This is some dummy copy. You\u2019re not really supposed to read this dummy copy, it is just a place holder for people who need some type to visualize what the actual copy might look like if it were real content.","profiles":[{"link":{"url":"https:\/\/facebook.com\/"},"name":"facebook","_id":"46b7917"},{"link":{"url":"https:\/\/twitter.com\/"},"name":"twitter","_id":"3f91eaa"},{"link":{"url":"https:\/\/linkedin.com\/"},"name":"linkedin","_id":"bcfef22"}],"button_text":"Show Details","image_padding":{"unit":"px","top":"0","right":"0","bottom":"0","left":"0","isLinked":true},"content_padding":{"unit":"px","top":"0","right":"0","bottom":"0","left":"0","isLinked":true},"title_spacing":{"unit":"px","size":17,"sizes":[]},"title_color":"#FFFFFF","title_typography_typography":"custom","title_typography_font_size":{"unit":"px","size":24,"sizes":[]},"title_typography_font_weight":"600","job_title_spacing":{"unit":"px","size":24,"sizes":[]},"job_title_color":"#888888","job_title_typography_typography":"custom","job_title_typography_font_size":{"unit":"px","size":16,"sizes":[]},"job_title_typography_font_weight":"normal","bio_spacing":{"unit":"px","size":16,"sizes":[]},"bio_color":"#FFFFFF","bio_typography_typography":"custom","bio_typography_font_size":{"unit":"px","size":16,"sizes":[]},"bio_typography_font_weight":"normal","bio_text_shadow_text_shadow_type":"yes","links_padding":{"unit":"px","size":0,"sizes":[]},"links_color":"#FFFFFF","_margin":{"unit":"px","top":"0","right":"0","bottom":"0","left":"0","isLinked":true},"_padding":{"unit":"px","top":"0","right":"0","bottom":"0","left":"0","isLinked":true}},"elements":[],"isInner":false,"widgetType":"wpzoom-elementor-addons-team-members","elType":"widget"}],"isInner":false,"elType":"column"},{"id":"405f19f","settings":{"_column_size":33,"_inline_size":null,"space_between_widgets":0,"margin":{"unit":"px","top":"0","right":"0","bottom":"0","left":"0","isLinked":true},"padding":{"unit":"px","top":"0","right":"0","bottom":"0","left":"0","isLinked":true}},"elements":[{"id":"1f3d5bd","settings":{"title":"Peggy Berlin","job_title":"Lead Designer","bio":"This is some dummy copy. You\u2019re not really supposed to read this dummy copy, it is just a place holder for people who need some type to visualize what the actual copy might look like if it were real content.","profiles":[{"link":{"url":"https:\/\/facebook.com\/"},"name":"facebook","_id":"46b7917"},{"link":{"url":"https:\/\/twitter.com\/"},"name":"twitter","_id":"3f91eaa"},{"link":{"url":"https:\/\/linkedin.com\/"},"name":"linkedin","_id":"bcfef22"}],"button_text":"Show Details","image_padding":{"unit":"px","top":"0","right":"0","bottom":"0","left":"0","isLinked":true},"content_padding":{"unit":"px","top":"0","right":"0","bottom":"0","left":"0","isLinked":true},"title_spacing":{"unit":"px","size":17,"sizes":[]},"title_color":"#FFFFFF","title_typography_typography":"custom","title_typography_font_size":{"unit":"px","size":24,"sizes":[]},"title_typography_font_weight":"600","job_title_spacing":{"unit":"px","size":24,"sizes":[]},"job_title_color":"#888888","job_title_typography_typography":"custom","job_title_typography_font_size":{"unit":"px","size":16,"sizes":[]},"job_title_typography_font_weight":"normal","bio_spacing":{"unit":"px","size":16,"sizes":[]},"bio_color":"#FFFFFF","bio_typography_typography":"custom","bio_typography_font_size":{"unit":"px","size":16,"sizes":[]},"bio_typography_font_weight":"normal","bio_text_shadow_text_shadow_type":"yes","links_padding":{"unit":"px","size":0,"sizes":[]},"links_color":"#FFFFFF","_margin":{"unit":"px","top":"0","right":"0","bottom":"0","left":"0","isLinked":true},"_padding":{"unit":"px","top":"0","right":"0","bottom":"0","left":"0","isLinked":true}},"elements":[],"isInner":false,"widgetType":"wpzoom-elementor-addons-team-members","elType":"widget"}],"isInner":false,"elType":"column"},{"id":"29919fbb","settings":{"_column_size":33,"_inline_size":null,"space_between_widgets":0,"margin":{"unit":"px","top":"0","right":"0","bottom":"0","left":"0","isLinked":true},"padding":{"unit":"px","top":"0","right":"0","bottom":"0","left":"0","isLinked":true}},"elements":[{"id":"5fd05dc3","settings":{"title":"Maria Alberts","job_title":"Designer","bio":"This is some dummy copy. You\u2019re not really supposed to read this dummy copy, it is just a place holder for people who need some type to visualize what the actual copy might look like if it were real content.","profiles":[{"link":{"url":"https:\/\/facebook.com\/"},"name":"facebook","_id":"46b7917"},{"link":{"url":"https:\/\/twitter.com\/"},"name":"twitter","_id":"3f91eaa"},{"link":{"url":"https:\/\/linkedin.com\/"},"name":"linkedin","_id":"bcfef22"}],"button_text":"Show Details","image_padding":{"unit":"px","top":"0","right":"0","bottom":"0","left":"0","isLinked":true},"content_padding":{"unit":"px","top":"0","right":"0","bottom":"0","left":"0","isLinked":true},"title_spacing":{"unit":"px","size":17,"sizes":[]},"title_color":"#FFFFFF","title_typography_typography":"custom","title_typography_font_size":{"unit":"px","size":24,"sizes":[]},"title_typography_font_weight":"600","job_title_spacing":{"unit":"px","size":24,"sizes":[]},"job_title_color":"#888888","job_title_typography_typography":"custom","job_title_typography_font_size":{"unit":"px","size":16,"sizes":[]},"job_title_typography_font_weight":"normal","bio_spacing":{"unit":"px","size":16,"sizes":[]},"bio_color":"#FFFFFF","bio_typography_typography":"custom","bio_typography_font_size":{"unit":"px","size":16,"sizes":[]},"bio_typography_font_weight":"normal","bio_text_shadow_text_shadow_type":"yes","links_padding":{"unit":"px","size":0,"sizes":[]},"links_color":"#FFFFFF","_margin":{"unit":"px","top":"0","right":"0","bottom":"0","left":"0","isLinked":true},"_padding":{"unit":"px","top":"0","right":"0","bottom":"0","left":"0","isLinked":true}},"elements":[],"isInner":false,"widgetType":"wpzoom-elementor-addons-team-members","elType":"widget"}],"isInner":false,"elType":"column"}],"isInner":false,"elType":"section"},{"id":"7f6dcc0e","settings":{"gap":"no","margin":{"unit":"px","top":"0","right":0,"bottom":"0","left":0,"isLinked":true},"padding":{"unit":"px","top":"100","right":"0","bottom":"0","left":"0","isLinked":false}},"elements":[{"id":"35bece74","settings":{"_column_size":100,"_inline_size":null,"space_between_widgets":0,"margin":{"unit":"px","top":"0","right":"0","bottom":"0","left":"0","isLinked":true},"padding":{"unit":"px","top":"0","right":"0","bottom":"0","left":"0","isLinked":true}},"elements":[{"id":"3c0f495","settings":{"title":"Our prices","title_color":"#0BB4AA","typography_typography":"custom","typography_font_size":{"unit":"px","size":36,"sizes":[]},"typography_font_weight":"500","_margin":{"unit":"px","top":"0","right":"0","bottom":"40","left":"0","isLinked":false}},"elements":[],"isInner":false,"widgetType":"heading","elType":"widget"}],"isInner":false,"elType":"column"}],"isInner":false,"elType":"section"},{"id":"2db510e4","settings":{"content_width":{"unit":"px","size":1240,"sizes":[]},"gap":"custom","gap_columns_custom":{"unit":"px","size":50,"sizes":[]},"structure":"40","margin":{"unit":"px","top":"0","right":0,"bottom":"0","left":0,"isLinked":true},"padding":{"unit":"px","top":"0","right":"0","bottom":"100","left":"0","isLinked":false}},"elements":[{"id":"5215f41f","settings":{"_column_size":25,"_inline_size":null,"space_between_widgets":0,"border_border":"solid","border_width":{"unit":"px","top":"0","right":"2","bottom":"0","left":"0","isLinked":false},"border_color":"#888888","margin":{"unit":"px","top":"0","right":"0","bottom":"0","left":"0","isLinked":true},"padding":{"unit":"px","top":"0","right":"0","bottom":"0","left":"0","isLinked":true}},"elements":[{"id":"68da899b","settings":{"title":"Payments","title_color":"#888888","typography_typography":"custom","typography_font_size":{"unit":"px","size":24,"sizes":[]},"typography_font_weight":"500","_margin":{"unit":"px","top":"0","right":"0","bottom":"40","left":"0","isLinked":false},"_padding":{"unit":"px","top":"0","right":"0","bottom":"0","left":"0","isLinked":true}},"elements":[],"isInner":false,"widgetType":"heading","elType":"widget"},{"id":"33c7e94e","settings":{"editor":"<p>Mauris sit amet diam<br \/>Nullam eget consectetur augue<br \/>Interdum et malesuada fames<br \/>Duis volutpat massa viverra<br \/>Maecenas posuere ante in eros<br \/>Nulla malesuada massa <br \/>Vestibulum scelerisque<\/p>","text_color":"#FFFFFF","typography_typography":"custom","typography_font_size":{"unit":"px","size":16,"sizes":[]},"typography_font_weight":"normal","typography_line_height":{"unit":"em","size":2,"sizes":[]},"_margin":{"unit":"px","top":"0","right":"0","bottom":"0","left":"0","isLinked":true},"_padding":{"unit":"px","top":"0","right":"0","bottom":"0","left":"0","isLinked":true}},"elements":[],"isInner":false,"widgetType":"text-editor","elType":"widget"}],"isInner":false,"elType":"column"},{"id":"508fdf15","settings":{"_column_size":25,"_inline_size":null,"space_between_widgets":0,"border_border":"solid","border_width":{"unit":"px","top":"0","right":"2","bottom":"0","left":"0","isLinked":false},"border_color":"#888888","border_radius":{"unit":"px","top":"0","right":"0","bottom":"0","left":"0","isLinked":false},"margin":{"unit":"px","top":"0","right":"0","bottom":"0","left":"0","isLinked":true},"padding":{"unit":"px","top":"0","right":"0","bottom":"0","left":"0","isLinked":true}},"elements":[{"id":"167f5589","settings":{"title":"Starter","price":"49","period":"Per Month","features_title":"Features","features_list":[{"text":"Standard Feature","icon":"fa fa-check","_id":"17b8bfe","__fa4_migrated":{"selected_icon":true}},{"text":"Another Great Feature","icon":"fa fa-check","_id":"8d499da","__fa4_migrated":{"selected_icon":true}},{"text":"Obsolete Feature","icon":"fa fa-close","_id":"605f237","selected_icon":{"value":"fas fa-times","library":"fa-solid"},"__fa4_migrated":{"selected_icon":true}},{"text":"Exciting Feature","icon":"fa fa-check","_id":"bedbe97","__fa4_migrated":{"selected_icon":true}}],"button_text":"Join today","badge_text":"Recommended","badge_position":"right","show_badge":"","title_color":"#0BB4AA","title_typography_typography":"custom","title_typography_font_size":{"unit":"px","size":24,"sizes":[]},"title_typography_font_weight":"500","price_color":"#FFFFFF","price_typography_typography":"custom","price_typography_font_weight":"400","currency_color":"#FFFFFF","currency_typography_typography":"custom","currency_typography_font_weight":"400","period_color":"#888888","period_typography_typography":"custom","period_typography_font_size":{"unit":"px","size":16,"sizes":[]},"period_typography_font_weight":"normal","features_title_color":"#FFFFFF","features_title_typography_typography":"custom","features_title_typography_font_size":{"unit":"px","size":16,"sizes":[]},"features_title_typography_font_weight":"600","features_list_color":"#CCCCCC","features_list_typography_typography":"custom","features_list_typography_font_size":{"unit":"px","size":16,"sizes":[]},"features_list_typography_font_weight":"normal","button_padding":{"unit":"px","top":"10","right":"25","bottom":"10","left":"25","isLinked":false},"button_border_border":"solid","button_border_width":{"unit":"px","top":"1","right":"1","bottom":"1","left":"1","isLinked":true},"button_border_radius":{"unit":"px","top":"100","right":"100","bottom":"100","left":"100","isLinked":true},"button_typography_typography":"custom","button_typography_font_size":{"unit":"px","size":16,"sizes":[]},"button_typography_font_weight":"500","button_typography_text_transform":"none","button_color":"#0BB4AA","button_bg_color":"#00000000","button_hover_color":"#FFFFFF","button_hover_bg_color":"#00000000","button_hover_border_color":"#FFFFFF","badge_bg_color":"#0BB4AA","badge_typography_typography":"custom","badge_typography_font_size":{"unit":"px","size":16,"sizes":[]},"badge_typography_font_weight":"500","_margin":{"unit":"px","top":"0","right":"0","bottom":"0","left":"0","isLinked":true},"_padding":{"unit":"px","top":"0","right":"0","bottom":"0","left":"0","isLinked":true}},"elements":[],"isInner":false,"widgetType":"wpzoom-elementor-addons-pricing-table","elType":"widget"}],"isInner":false,"elType":"column"},{"id":"4f94200d","settings":{"_column_size":25,"_inline_size":null,"space_between_widgets":0,"border_border":"solid","border_width":{"unit":"px","top":"0","right":"2","bottom":"0","left":"0","isLinked":false},"border_color":"#888888","margin":{"unit":"px","top":"0","right":"0","bottom":"0","left":"0","isLinked":true},"padding":{"unit":"px","top":"0","right":"0","bottom":"0","left":"0","isLinked":true}},"elements":[{"id":"5662ae32","settings":{"title":"Premium","price":"99","period":"Per Month","features_title":"Features","features_list":[{"text":"Standard Feature","icon":"fa fa-check","_id":"1f14612"},{"text":"Another Great Feature","icon":"fa fa-check","_id":"12f4b7c"},{"text":"Obsolete Feature","icon":"fa fa-close","_id":"4322aac"},{"text":"Exciting Feature","icon":"fa fa-check","_id":"d531d15"}],"button_text":"Join today","badge_text":"Recommended","badge_position":"right","title_color":"#0BB4AA","title_typography_typography":"custom","title_typography_font_size":{"unit":"px","size":24,"sizes":[]},"title_typography_font_weight":"500","price_color":"#FFFFFF","price_typography_typography":"custom","price_typography_font_weight":"400","currency_color":"#FFFFFF","currency_typography_typography":"custom","currency_typography_font_weight":"400","period_color":"#888888","period_typography_typography":"custom","period_typography_font_size":{"unit":"px","size":16,"sizes":[]},"period_typography_font_weight":"normal","features_title_color":"#FFFFFF","features_title_typography_typography":"custom","features_title_typography_font_size":{"unit":"px","size":16,"sizes":[]},"features_title_typography_font_weight":"600","features_list_color":"#CCCCCC","features_list_typography_typography":"custom","features_list_typography_font_size":{"unit":"px","size":16,"sizes":[]},"features_list_typography_font_weight":"normal","button_padding":{"unit":"px","top":"10","right":"25","bottom":"10","left":"25","isLinked":false},"button_border_border":"solid","button_border_width":{"unit":"px","top":"1","right":"1","bottom":"1","left":"1","isLinked":true},"button_border_radius":{"unit":"px","top":"100","right":"100","bottom":"100","left":"100","isLinked":true},"button_typography_typography":"custom","button_typography_font_size":{"unit":"px","size":16,"sizes":[]},"button_typography_font_weight":"500","button_typography_text_transform":"none","button_color":"#0BB4AA","button_bg_color":"#00000000","button_hover_color":"#FFFFFF","button_hover_bg_color":"#00000000","button_hover_border_color":"#FFFFFF","badge_bg_color":"#0BB4AA","badge_typography_typography":"custom","badge_typography_font_size":{"unit":"px","size":16,"sizes":[]},"badge_typography_font_weight":"500","_margin":{"unit":"px","top":"0","right":"0","bottom":"0","left":"0","isLinked":true},"_padding":{"unit":"px","top":"0","right":"0","bottom":"0","left":"0","isLinked":true}},"elements":[],"isInner":false,"widgetType":"wpzoom-elementor-addons-pricing-table","elType":"widget"}],"isInner":false,"elType":"column"},{"id":"55fdc233","settings":{"_column_size":25,"_inline_size":null,"space_between_widgets":0,"margin":{"unit":"px","top":"0","right":"0","bottom":"0","left":"0","isLinked":true},"padding":{"unit":"px","top":"0","right":"0","bottom":"0","left":"0","isLinked":true}},"elements":[{"id":"34b77270","settings":{"title":"Expert","price":"199","period":"Per Month","features_title":"Features","features_list":[{"text":"Standard Feature","icon":"fa fa-check","_id":"ff52646"},{"text":"Another Great Feature","icon":"fa fa-check","_id":"3dac443"},{"text":"Obsolete Feature","icon":"fa fa-close","_id":"92f8d92"},{"text":"Exciting Feature","icon":"fa fa-check","_id":"6221f04"}],"button_text":"Join today","badge_text":"Recommended","show_badge":"","badge_position":"right","title_color":"#0BB4AA","title_typography_typography":"custom","title_typography_font_size":{"unit":"px","size":24,"sizes":[]},"title_typography_font_weight":"500","price_color":"#FFFFFF","price_typography_typography":"custom","price_typography_font_weight":"400","currency_color":"#FFFFFF","currency_typography_typography":"custom","currency_typography_font_weight":"400","period_color":"#888888","period_typography_typography":"custom","period_typography_font_size":{"unit":"px","size":16,"sizes":[]},"period_typography_font_weight":"normal","features_title_color":"#FFFFFF","features_title_typography_typography":"custom","features_title_typography_font_size":{"unit":"px","size":16,"sizes":[]},"features_title_typography_font_weight":"600","features_list_color":"#CCCCCC","features_list_typography_typography":"custom","features_list_typography_font_size":{"unit":"px","size":16,"sizes":[]},"features_list_typography_font_weight":"normal","button_padding":{"unit":"px","top":"10","right":"25","bottom":"10","left":"25","isLinked":false},"button_border_border":"solid","button_border_width":{"unit":"px","top":"1","right":"1","bottom":"1","left":"1","isLinked":true},"button_border_radius":{"unit":"px","top":"100","right":"100","bottom":"100","left":"100","isLinked":true},"button_typography_typography":"custom","button_typography_font_size":{"unit":"px","size":16,"sizes":[]},"button_typography_font_weight":"500","button_typography_text_transform":"none","button_color":"#0BB4AA","button_bg_color":"#00000000","button_hover_color":"#FFFFFF","button_hover_bg_color":"#00000000","button_hover_border_color":"#FFFFFF","badge_bg_color":"#0BB4AA","badge_typography_typography":"custom","badge_typography_font_size":{"unit":"px","size":16,"sizes":[]},"badge_typography_font_weight":"500","_margin":{"unit":"px","top":"0","right":"0","bottom":"0","left":"0","isLinked":true},"_padding":{"unit":"px","top":"0","right":"0","bottom":"0","left":"0","isLinked":true}},"elements":[],"isInner":false,"widgetType":"wpzoom-elementor-addons-pricing-table","elType":"widget"}],"isInner":false,"elType":"column"}],"isInner":false,"elType":"section"},{"id":"4f4a9c03","settings":{"gap":"no","margin":{"unit":"px","top":"0","right":0,"bottom":"0","left":0,"isLinked":true},"padding":{"unit":"px","top":"100","right":"0","bottom":"100","left":"0","isLinked":false}},"elements":[{"id":"4b1cfc8b","settings":{"_column_size":100,"_inline_size":null,"space_between_widgets":0,"margin":{"unit":"px","top":"0","right":"0","bottom":"0","left":"0","isLinked":true},"padding":{"unit":"px","top":"0","right":"0","bottom":"0","left":"0","isLinked":true}},"elements":[{"id":"38dc88cc","settings":{"title":"Blog","title_color":"#0BB4AA","typography_typography":"custom","typography_font_size":{"unit":"px","size":36,"sizes":[]},"typography_font_weight":"500","_margin":{"unit":"px","top":"0","right":"0","bottom":"40","left":"0","isLinked":false}},"elements":[],"isInner":false,"widgetType":"heading","elType":"widget"},{"id":"4d129a01","settings":{"meta_data":[],"meta_separator":"\/","read_more_text":"Read More &rarr;","grid_style_columns_margin":{"unit":"px","size":30,"sizes":[]},"grid_style_image_margin":{"unit":"px","top":"0","right":"0","bottom":"30","left":"0","isLinked":false},"grid_title_style_typography_typography":"custom","grid_title_style_typography_font_size":{"unit":"px","size":24,"sizes":[]},"grid_title_style_typography_font_weight":"500","grid_title_style_color":"#FFFFFF","grid_title_style_margin":{"unit":"px","top":"0","right":"0","bottom":"20","left":"0","isLinked":false},"grid_content_style_typography_typography":"custom","grid_content_style_typography_font_size":{"unit":"px","size":16,"sizes":[]},"grid_content_style_typography_font_weight":"normal","grid_content_style_typography_line_height":{"unit":"em","size":1.75,"sizes":[]},"grid_content_style_color":"#FFFFFF","grid_content_style_margin":{"unit":"px","top":"0","right":"0","bottom":"0","left":"0","isLinked":true},"grid_readmore_style_typography_typography":"custom","grid_readmore_style_typography_font_size":{"unit":"px","size":16,"sizes":[]},"grid_readmore_style_typography_font_weight":"600","grid_readmore_style_color":"#FFFFFF","grid_readmore_style_margin":{"unit":"px","top":"20","right":"0","bottom":"0","left":"0","isLinked":false},"_margin":{"unit":"px","top":"0","right":"0","bottom":"0","left":"0","isLinked":true},"_padding":{"unit":"px","top":"0","right":"0","bottom":"0","left":"0","isLinked":true}},"elements":[],"isInner":false,"widgetType":"wpzoom-elementor-addons-posts-grid","elType":"widget"},{"id":"d47596b","settings":{"text":"View all articles","align":"center","size":"lg","typography_typography":"custom","typography_font_size":{"unit":"px","size":16,"sizes":[]},"typography_font_weight":"500","button_text_color":"#0BB4AA","background_color":"#00000000","border_border":"solid","border_width":{"unit":"px","top":"1","right":"1","bottom":"1","left":"1","isLinked":true},"border_color":"#0BB4AA","border_radius":{"unit":"px","top":"100","right":"100","bottom":"100","left":"100","isLinked":true},"_margin":{"unit":"px","top":"60","right":"0","bottom":"0","left":"0","isLinked":false}},"elements":[],"isInner":false,"widgetType":"button","elType":"widget"}],"isInner":false,"elType":"column"}],"isInner":false,"elType":"section"},{"id":"7a3b3b35","settings":{"gap":"no","margin":{"unit":"px","top":"0","right":0,"bottom":"0","left":0,"isLinked":true},"padding":{"unit":"px","top":"0","right":"0","bottom":"100","left":"0","isLinked":false}},"elements":[{"id":"686ee125","settings":{"_column_size":100,"_inline_size":null,"space_between_widgets":0,"margin":{"unit":"px","top":"0","right":"0","bottom":"0","left":"0","isLinked":true},"padding":{"unit":"px","top":"0","right":"0","bottom":"0","left":"0","isLinked":true}},"elements":[{"id":"1b9b2e4a","settings":{"text":"Divider","color":"#888888","gap":{"unit":"px","size":2,"sizes":[]},"_margin":{"unit":"px","top":"0","right":"0","bottom":"100","left":"0","isLinked":false},"_padding":{"unit":"px","top":"0","right":"0","bottom":"0","left":"0","isLinked":true}},"elements":[],"isInner":false,"widgetType":"divider","elType":"widget"},{"id":"3871914c","settings":{"title":"Let's work together!","title_color":"#0BB4AA","typography_typography":"custom","typography_font_size":{"unit":"px","size":60,"sizes":[]},"typography_font_weight":"500","_margin":{"unit":"px","top":"0","right":"0","bottom":"0","left":"0","isLinked":true},"_padding":{"unit":"px","top":"0","right":"0","bottom":"0","left":"0","isLinked":true}},"elements":[],"isInner":false,"widgetType":"heading","elType":"widget"},{"id":"3de44163","settings":{"text":"Get in touch","align":"left","size":"lg","typography_typography":"custom","typography_font_size":{"unit":"px","size":16,"sizes":[]},"typography_font_weight":"500","button_text_color":"#0BB4AA","background_color":"#00000000","border_border":"solid","border_width":{"unit":"px","top":"1","right":"1","bottom":"1","left":"1","isLinked":true},"border_color":"#0BB4AA","border_radius":{"unit":"px","top":"100","right":"100","bottom":"100","left":"100","isLinked":true},"_margin":{"unit":"px","top":"60","right":"0","bottom":"0","left":"0","isLinked":false}},"elements":[],"isInner":false,"widgetType":"button","elType":"widget"}],"isInner":false,"elType":"column"}],"isInner":false,"elType":"section"}]}